{"type": "Feature", "id": 12510423, "properties": {"woe:id": 12510423, "woe:parent_id": 2213857, "woe:name": "Oktember Highway Strip Airport", "woe:placetype": 14, "woe:placetype_name": "Airport", "woe:lang": "ENG", "iso:country": "AM", "meta:provider": ["geoplanet:7.3.1", "geoplanet:7.3.2", "geoplanet:7.4.0", "geoplanet:7.4.1", "geoplanet:7.5.1", "geoplanet:7.5.2", "geoplanet:7.6.0", "geoplanet:7.8.1", "geoplanet:7.9.0", "geoplanet:7.10.0", "geoplanet:8.0.0", "woeplanet:8.0.0"], "meta:indexed": "2020-08-20T20:28:14.290933", "meta:updated": "2020-08-22T01:58:34.739405", "woe:hierarchy": {"continent": 24865671, "country": 23424743, "town": 0, "planet": 1, "county": 15022552, "suburb": 0, "state": 20070210, "region": 0, "localadmin": 0}, "woe:timezone_id": 28350867, "woe:hash": "szphnbfkmkfb", "woe:centroid": [43.8937, 40.083], "geom:latitude": 40.083, "geom:longitude": 43.8937, "geom:hash": "szphnbfkmkfb", "woe:latitude": 40.083, "geom:centroid": [43.8937, 40.083], "woe:longitude": 43.8937, "woe:repo": "woeplanet-airport-am"}, "geometry": {"coordinates": [43.8937, 40.083], "type": "Point"}}